dex_adaptors/__init__.py
dex_adaptors/aave_v3.py
dex_adaptors/balancer_v2.py
dex_adaptors/compound_v2.py
dex_adaptors/curve.py
dex_adaptors/morpho.py
dex_adaptors/pendle.py
dex_adaptors/silo.py
dex_adaptors/uniswap_v3.py
dex_adaptors/exchange/__init__.py
dex_adaptors/exchange/aave_v3.py
dex_adaptors/exchange/balancer_v2.py
dex_adaptors/exchange/base.py
dex_adaptors/exchange/compound_v2.py
dex_adaptors/exchange/curve.py
dex_adaptors/exchange/morpho.py
dex_adaptors/exchange/pendle.py
dex_adaptors/exchange/silo.py
dex_adaptors/exchange/uniswap_v3.py
dex_adaptors/parsers/__init__.py
dex_adaptors/parsers/aave_v3.py
dex_adaptors/parsers/balancer_v2.py
dex_adaptors/parsers/base.py
dex_adaptors/parsers/compound_v2.py
dex_adaptors/parsers/curve.py
dex_adaptors/parsers/morpho.py
dex_adaptors/parsers/pendle.py
dex_adaptors/parsers/silo.py
dex_adaptors/parsers/uniswap_v3.py
dex_adaptors-0.0.4.dist-info/METADATA
dex_adaptors-0.0.4.dist-info/WHEEL
dex_adaptors-0.0.4.dist-info/top_level.txt
dex_adaptors-0.0.4.dist-info/RECORD
