Metadata-Version: 2.1
Name: dex-adaptors
Version: 0.0.4
Requires-Dist: aiohttp ==3.9.5
Requires-Dist: aiosignal ==1.3.1
Requires-Dist: anyio ==4.3.0
Requires-Dist: async-timeout ==4.0.3
Requires-Dist: attrs ==23.2.0
Requires-Dist: backoff ==2.2.1
Requires-Dist: backports.tarfile ==1.1.1
Requires-Dist: cachetools ==5.3.3
Requires-Dist: certifi ==2024.2.2
Requires-Dist: cfgv ==3.4.0
Requires-Dist: charset-normalizer ==3.3.2
Requires-Dist: colorama ==0.4.6
Requires-Dist: contourpy ==1.2.1
Requires-Dist: cycler ==0.12.1
Requires-Dist: distlib ==0.3.8
Requires-Dist: docutils ==0.21.2
Requires-Dist: exceptiongroup ==1.2.1
Requires-Dist: filelock ==3.14.0
Requires-Dist: fonttools ==4.52.4
Requires-Dist: frozenlist ==1.4.1
Requires-Dist: google-api-core ==2.19.0
Requires-Dist: google-api-python-client ==2.129.0
Requires-Dist: google-auth ==2.29.0
Requires-Dist: google-auth-httplib2 ==0.2.0
Requires-Dist: google-auth-oauthlib ==1.2.0
Requires-Dist: googleapis-common-protos ==1.63.0
Requires-Dist: gql ==3.5.0
Requires-Dist: graphql-core ==3.2.3
Requires-Dist: httplib2 ==0.22.0
Requires-Dist: identify ==2.5.36
Requires-Dist: idna ==3.7
Requires-Dist: importlib-metadata ==7.1.0
Requires-Dist: iniconfig ==2.0.0
Requires-Dist: jaraco.classes ==3.4.0
Requires-Dist: jaraco.context ==5.3.0
Requires-Dist: jaraco.functools ==4.0.1
Requires-Dist: keyring ==25.2.0
Requires-Dist: kiwisolver ==1.4.5
Requires-Dist: markdown-it-py ==3.0.0
Requires-Dist: matplotlib ==3.9.0
Requires-Dist: mdurl ==0.1.2
Requires-Dist: more-itertools ==10.2.0
Requires-Dist: multidict ==6.0.5
Requires-Dist: nh3 ==0.2.17
Requires-Dist: nodeenv ==1.8.0
Requires-Dist: numpy ==1.26.4
Requires-Dist: oauthlib ==3.2.2
Requires-Dist: packaging ==24.0
Requires-Dist: pandas ==2.2.2
Requires-Dist: pillow ==10.3.0
Requires-Dist: pkginfo ==1.10.0
Requires-Dist: platformdirs ==4.2.1
Requires-Dist: pluggy ==1.5.0
Requires-Dist: pre-commit ==3.7.0
Requires-Dist: proto-plus ==1.23.0
Requires-Dist: protobuf ==4.25.3
Requires-Dist: pyasn1 ==0.6.0
Requires-Dist: pyasn1-modules ==0.4.0
Requires-Dist: Pygments ==2.18.0
Requires-Dist: pygsheets ==2.0.6
Requires-Dist: pyparsing ==3.1.2
Requires-Dist: pytest ==8.2.0
Requires-Dist: python-dateutil ==2.9.0.post0
Requires-Dist: python-dotenv ==1.0.1
Requires-Dist: pytz ==2024.1
Requires-Dist: pywin32-ctypes ==0.2.2
Requires-Dist: PyYAML ==6.0.1
Requires-Dist: readme-renderer ==43.0
Requires-Dist: requests ==2.31.0
Requires-Dist: requests-oauthlib ==2.0.0
Requires-Dist: requests-toolbelt ==1.0.0
Requires-Dist: rfc3986 ==2.0.0
Requires-Dist: rich ==13.7.1
Requires-Dist: rsa ==4.9
Requires-Dist: six ==1.16.0
Requires-Dist: sniffio ==1.3.1
Requires-Dist: tomli ==2.0.1
Requires-Dist: twine ==5.0.0
Requires-Dist: typing-extensions ==4.11.0
Requires-Dist: tzdata ==2024.1
Requires-Dist: uritemplate ==4.1.1
Requires-Dist: urllib3 ==2.2.1
Requires-Dist: virtualenv ==20.26.1
Requires-Dist: yarl ==1.9.4
Requires-Dist: zipp ==3.18.1
